phylmaker/__init__.py
phylmaker/__version__.py
phylmaker/exceptions.py
phylmaker/query.py
phylmaker/result.py
phylmaker/server.py
phylmaker/test/__init__.py
phylmaker/test/base.py
phylmaker/test/test_query.py
phylmaker/test/test_results.py
phylmaker/test/test_server.py
phylmaker-1.2.dist-info/DESCRIPTION.rst
phylmaker-1.2.dist-info/METADATA
phylmaker-1.2.dist-info/RECORD
phylmaker-1.2.dist-info/WHEEL
phylmaker-1.2.dist-info/metadata.json
phylmaker-1.2.dist-info/top_level.txt
