Metadata-Version: 2.0
Name: phylmaker
Version: 1.2
Summary: A Pythonic wrapper for the FileMaker Server XML API/interface
Home-page: https://bitbucket.org/Raumkraut/phylmaker
Author: Mel Collins
Author-email: mel@raumkraut.net
License: MIT License
Platform: OS Independent
Classifier: Development Status :: 5 - Production/Stable
Classifier: Intended Audience :: Developers
Classifier: License :: OSI Approved :: MIT License
Classifier: Operating System :: OS Independent
Classifier: Programming Language :: Python
Classifier: Topic :: Database :: Front-Ends
Requires-Dist: requests (>=1.0)
